lib/__init__.py
lib/SAAT.py
lib/utils.py
saat-1.0.0.dist-info/METADATA
saat-1.0.0.dist-info/WHEEL
saat-1.0.0.dist-info/RECORD
